tech/__init__.py
tech/mlsql/__init__.py
tech/mlsql/plugin/__init__.py
tech/mlsql/plugin/ds/coco/__init__.py
byzer_cocodataset-0.1.0.dist-info/METADATA
byzer_cocodataset-0.1.0.dist-info/WHEEL
byzer_cocodataset-0.1.0.dist-info/top_level.txt
byzer_cocodataset-0.1.0.dist-info/RECORD
