Metadata-Version: 2.1
Name: byzer-cocodataset
Version: 0.1.0
Summary: Byzer tool to generate cocodata meta file
Home-page: https://github.com/allwefantasy/byzer-cocodataset
Author: WilliamZhu
Author-email: allwefantasy@gmail.com
License: http://www.apache.org/licenses/LICENSE-2.0
Platform: UNKNOWN
Classifier: Development Status :: 5 - Production/Stable
Classifier: License :: OSI Approved :: Apache Software License
Classifier: Programming Language :: Python :: 3.6
Classifier: Programming Language :: Python :: 3.7
Classifier: Programming Language :: Python :: Implementation :: CPython
Classifier: Programming Language :: Python :: Implementation :: PyPy
Requires-Dist: numpy
Requires-Dist: pandas
Requires-Dist: pypandoc
Requires-Dist: Pillow
